hbayes/__init__.py
hbayes/bayesian_optimization.py
hbayes/domain_reduction.py
hbayes/event.py
hbayes/logger.py
hbayes/target_space.py
hbayes/util.py
hbayes/config/__init__.py
hbayes/config/meta.py
hbayes-0.0.1.dist-info/LICENSE
hbayes-0.0.1.dist-info/METADATA
hbayes-0.0.1.dist-info/WHEEL
hbayes-0.0.1.dist-info/top_level.txt
hbayes-0.0.1.dist-info/RECORD
